{
    "start_time": 1555642533.2470772,
    "target": "cnt",
    "server_path": "/Users/newzysharma/.Trash/REcPf/vJKtc/UqpeM/YC0N4/kuMpm",
    "data_path": "/Users/newzysharma/Desktop/Desktop/info6105/INFO6105-FinalProject/INFO6105-FinalProject/MetaData/hour.csv",
    "test_path": null,
    "max_models": 9,
    "run_time": 500,
    "run_id": "qB7KF",
    "scale": false,
    "classification": false,
    "model_path": null,
    "balance": false,
    "balance_threshold": 0.2,
    "project": null,
    "end_time": 1555643426.2017002,
    "execution_time": 892.9546229839325,
    "run_path": "/Users/newzysharma/.Trash/REcPf/vJKtc/UqpeM/YC0N4/kuMpm/qB7KF",
    "nthreads": 1,
    "min_mem_size": 1,
    "analysis": 0,
    "X": [
        "instant",
        "season",
        "yr",
        "mnth",
        "hr",
        "holiday",
        "weekday",
        "workingday",
        "weathersit",
        "casual",
        "registered",
        "dteday",
        "temp",
        "atemp",
        "hum",
        "windspeed"
    ],
    "variables": {
        "instant": "int",
        "dteday": "time",
        "season": "int",
        "yr": "int",
        "mnth": "int",
        "hr": "int",
        "holiday": "int",
        "weekday": "int",
        "workingday": "int",
        "weathersit": "int",
        "temp": "real",
        "atemp": "real",
        "hum": "real",
        "windspeed": "real",
        "casual": "int",
        "registered": "int",
        "cnt": "int"
    },
    "model_execution_time_sec": 805.7412900924683,
    "model_execution_time": 807.5188817977905,
    "mod_best": "XGBoost_3_AutoML_20190418_225633",
    "mod_best_algo": "xgboost",
    "models": [
        "XGBoost_3_AutoML_20190418_225633",
        "DRF_1_AutoML_20190418_225633",
        "GBM_1_AutoML_20190418_225633",
        "GLM_grid_1_AutoML_20190418_225633_model_1",
        "StackedEnsemble_BestOfFamily_AutoML_20190418_225633"
    ]
}
